SQLServerToPandasDataFrame/__init__.py
SQLServerToPandasDataFrame_germanandresjejencortes-0.0.2.dist-info/LICENSE
SQLServerToPandasDataFrame_germanandresjejencortes-0.0.2.dist-info/METADATA
SQLServerToPandasDataFrame_germanandresjejencortes-0.0.2.dist-info/WHEEL
SQLServerToPandasDataFrame_germanandresjejencortes-0.0.2.dist-info/top_level.txt
SQLServerToPandasDataFrame_germanandresjejencortes-0.0.2.dist-info/RECORD
