Metadata-Version: 2.1
Name: SQLServerToPandasDataFrame-germanandresjejencortes
Version: 0.0.2
Summary: Query Data from a Private DataBase and save it in a Pandas DataFrame
Home-page: https://github.com/AndresJejen/MicrosoftSQLServerToPandasDataFrame
Author: Andres Jejen
Author-email: gajcam@gmail.com
License: UNKNOWN
Platform: UNKNOWN
Classifier: Programming Language :: Python :: 3
Classifier: License :: OSI Approved :: MIT License
Classifier: Operating System :: OS Independent
Requires-Python: >=3.6
Requires-Dist: pyodbc
Requires-Dist: pandas
